expyfun/__init__.py
expyfun/_experiment_controller.py
expyfun/_eyelink_controller.py
expyfun/_fixes.py
expyfun/_input_controllers.py
expyfun/_parallel.py
expyfun/_tdt_controller.py
expyfun/_trigger_controllers.py
expyfun/_utils.py
expyfun/_version.py
expyfun/conftest.py
expyfun/_sound_controllers/__init__.py
expyfun/_sound_controllers/_pyglet.py
expyfun/_sound_controllers/_rtmixer.py
expyfun/_sound_controllers/_sound_controller.py
expyfun/_sound_controllers/_sounddevice.py
expyfun/analyze/__init__.py
expyfun/analyze/_analyze.py
expyfun/analyze/_recon.py
expyfun/analyze/_viz.py
expyfun/analyze/tests/__init__.py
expyfun/analyze/tests/test_analyze_functions.py
expyfun/analyze/tests/test_recon.py
expyfun/analyze/tests/test_viz.py
expyfun/codeblocks/__init__.py
expyfun/codeblocks/_pupillometry.py
expyfun/io/__init__.py
expyfun/io/_parse.py
expyfun/io/_wav.py
expyfun/io/tests/__init__.py
expyfun/io/tests/test_parse.py
expyfun/io/tests/test_wav.py
expyfun/stimuli/__init__.py
expyfun/stimuli/_crm.py
expyfun/stimuli/_hrtf.py
expyfun/stimuli/_mls.py
expyfun/stimuli/_stimuli.py
expyfun/stimuli/_texture.py
expyfun/stimuli/_tracker.py
expyfun/stimuli/_vocoder.py
expyfun/stimuli/tests/__init__.py
expyfun/stimuli/tests/test_mls.py
expyfun/stimuli/tests/test_stimuli.py
expyfun/stimuli/tests/test_tracker.py
expyfun/tests/__init__.py
expyfun/tests/test_docstring_parameters.py
expyfun/tests/test_experiment_controller.py
expyfun/tests/test_eyelink_controller.py
expyfun/tests/test_logging.py
expyfun/tests/test_parallel.py
expyfun/tests/test_trigger_conversion.py
expyfun/tests/test_utils.py
expyfun/visual/__init__.py
expyfun/visual/_visual.py
expyfun/visual/tests/__init__.py
expyfun/visual/tests/test_visuals.py
expyfun-3.0.0.dist-info/METADATA
expyfun-3.0.0.dist-info/WHEEL
expyfun-3.0.0.dist-info/licenses/LICENSE
expyfun-3.0.0.dist-info/RECORD
