Metadata-Version: 2.4
Name: expyfun
Version: 3.0.0
Summary: A high-precision auditory and visual stimulus delivery library for psychoacoustics in Python.
Author-email: Daniel McCloy <dan@mccloy.info>, Eric Larson <larsoner@uw.edu>, Ross Maddox <rkmaddox@uw.edu>
Maintainer-email: Daniel McCloy <dan@mccloy.info>, Eric Larson <larsoner@uw.edu>
License-Expression: BSD-3-Clause
License-File: LICENSE
Keywords: experiment,psychoacoustics,psychophysics,stimuli
Classifier: Intended Audience :: Developers
Classifier: Intended Audience :: Science/Research
Classifier: Operating System :: MacOS
Classifier: Operating System :: Microsoft :: Windows
Classifier: Operating System :: POSIX
Classifier: Operating System :: Unix
Classifier: Programming Language :: Python
Classifier: Topic :: Scientific/Engineering
Classifier: Topic :: Software Development
Requires-Python: >=3.10
Requires-Dist: decorator
Requires-Dist: h5io
Requires-Dist: matplotlib
Requires-Dist: numpy
Requires-Dist: packaging
Requires-Dist: pillow
Requires-Dist: pyglet>=2
Requires-Dist: scipy
Provides-Extra: all
Requires-Dist: joblib; extra == 'all'
Requires-Dist: mne; extra == 'all'
Requires-Dist: pandas; extra == 'all'
Requires-Dist: pyparallel; extra == 'all'
Requires-Dist: rtmixer; extra == 'all'
Requires-Dist: tdtpy; (platform_system == 'Windows') and extra == 'all'
